{"name": "DIC-C2DH-HeLa-01/Mu-Lux-CZ/01_RES", "num_timestep": 115, "lineage": [{"id": "1", "birth": "0", "death": "66", "parent": "0"}, {"id": "2", "birth": "0", "death": "22", "parent": "0"}, {"id": "3", "birth": "0", "death": "100", "parent": "0"}, {"id": "4", "birth": "0", "death": "22", "parent": "0"}, {"id": "5", "birth": "0", "death": "95", "parent": "0"}, {"id": "6", "birth": "0", "death": "0", "parent": "0"}, {"id": "7", "birth": "0", "death": "55", "parent": "0"}, {"id": "8", "birth": "0", "death": "1", "parent": "0"}, {"id": "9", "birth": "0", "death": "4", "parent": "0"}, {"id": "10", "birth": "0", "death": "8", "parent": "0"}, {"id": "11", "birth": "0", "death": "12", "parent": "0"}, {"id": "12", "birth": "1", "death": "12", "parent": "6"}, {"id": "13", "birth": "1", "death": "1", "parent": "6"}, {"id": "14", "birth": "2", "death": "6", "parent": "8"}, {"id": "15", "birth": "2", "death": "3", "parent": "8"}, {"id": "16", "birth": "5", "death": "74", "parent": "9"}, {"id": "17", "birth": "5", "death": "13", "parent": "9"}, {"id": "18", "birth": "7", "death": "46", "parent": "14"}, {"id": "19", "birth": "7", "death": "9", "parent": "14"}, {"id": "20", "birth": "10", "death": "114", "parent": "19"}, {"id": "21", "birth": "10", "death": "114", "parent": "19"}, {"id": "22", "birth": "13", "death": "13", "parent": "12"}, {"id": "23", "birth": "13", "death": "14", "parent": "12"}, {"id": "24", "birth": "14", "death": "45", "parent": "17"}, {"id": "25", "birth": "14", "death": "28", "parent": "17"}, {"id": "26", "birth": "15", "death": "15", "parent": "23"}, {"id": "27", "birth": "15", "death": "18", "parent": "23"}, {"id": "28", "birth": "19", "death": "19", "parent": "27"}, {"id": "29", "birth": "19", "death": "28", "parent": "27"}, {"id": "30", "birth": "23", "death": "23", "parent": "2"}, {"id": "31", "birth": "23", "death": "55", "parent": "2"}, {"id": "32", "birth": "26", "death": "27", "parent": "0"}, {"id": "33", "birth": "29", "death": "29", "parent": "0"}, {"id": "34", "birth": "29", "death": "46", "parent": "0"}, {"id": "35", "birth": "29", "death": "29", "parent": "29"}, {"id": "36", "birth": "29", "death": "58", "parent": "29"}, {"id": "37", "birth": "30", "death": "37", "parent": "0"}, {"id": "38", "birth": "33", "death": "33", "parent": "0"}, {"id": "39", "birth": "35", "death": "36", "parent": "0"}, {"id": "40", "birth": "39", "death": "40", "parent": "0"}, {"id": "41", "birth": "42", "death": "43", "parent": "0"}, {"id": "42", "birth": "45", "death": "59", "parent": "0"}, {"id": "43", "birth": "46", "death": "47", "parent": "24"}, {"id": "44", "birth": "46", "death": "46", "parent": "24"}, {"id": "45", "birth": "47", "death": "47", "parent": "34"}, {"id": "46", "birth": "47", "death": "99", "parent": "34"}, {"id": "47", "birth": "47", "death": "48", "parent": "18"}, {"id": "48", "birth": "47", "death": "48", "parent": "18"}, {"id": "49", "birth": "48", "death": "107", "parent": "43"}, {"id": "50", "birth": "48", "death": "48", "parent": "43"}, {"id": "51", "birth": "49", "death": "49", "parent": "48"}, {"id": "52", "birth": "49", "death": "49", "parent": "48"}, {"id": "53", "birth": "50", "death": "50", "parent": "51"}, {"id": "54", "birth": "50", "death": "50", "parent": "51"}, {"id": "55", "birth": "50", "death": "52", "parent": "0"}, {"id": "56", "birth": "51", "death": "52", "parent": "54"}, {"id": "57", "birth": "51", "death": "51", "parent": "54"}, {"id": "58", "birth": "53", "death": "53", "parent": "56"}, {"id": "59", "birth": "53", "death": "56", "parent": "56"}, {"id": "60", "birth": "53", "death": "53", "parent": "56"}, {"id": "61", "birth": "56", "death": "56", "parent": "0"}, {"id": "62", "birth": "56", "death": "99", "parent": "31"}, {"id": "63", "birth": "56", "death": "56", "parent": "31"}, {"id": "64", "birth": "56", "death": "56", "parent": "7"}, {"id": "65", "birth": "56", "death": "56", "parent": "7"}, {"id": "66", "birth": "57", "death": "57", "parent": "59"}, {"id": "67", "birth": "57", "death": "58", "parent": "59"}, {"id": "68", "birth": "57", "death": "67", "parent": "59"}, {"id": "69", "birth": "59", "death": "61", "parent": "36"}, {"id": "70", "birth": "59", "death": "59", "parent": "36"}, {"id": "71", "birth": "59", "death": "64", "parent": "67"}, {"id": "72", "birth": "59", "death": "61", "parent": "67"}, {"id": "73", "birth": "61", "death": "62", "parent": "0"}, {"id": "74", "birth": "62", "death": "62", "parent": "0"}, {"id": "75", "birth": "62", "death": "74", "parent": "69"}, {"id": "76", "birth": "62", "death": "62", "parent": "69"}, {"id": "77", "birth": "64", "death": "68", "parent": "0"}, {"id": "78", "birth": "64", "death": "64", "parent": "0"}, {"id": "79", "birth": "65", "death": "72", "parent": "71"}, {"id": "80", "birth": "65", "death": "65", "parent": "71"}, {"id": "81", "birth": "67", "death": "68", "parent": "1"}, {"id": "82", "birth": "67", "death": "70", "parent": "1"}, {"id": "83", "birth": "68", "death": "71", "parent": "68"}, {"id": "84", "birth": "68", "death": "68", "parent": "68"}, {"id": "85", "birth": "68", "death": "68", "parent": "68"}, {"id": "86", "birth": "68", "death": "68", "parent": "0"}, {"id": "87", "birth": "68", "death": "68", "parent": "68"}, {"id": "88", "birth": "71", "death": "71", "parent": "82"}, {"id": "89", "birth": "71", "death": "74", "parent": "82"}, {"id": "90", "birth": "72", "death": "72", "parent": "83"}, {"id": "91", "birth": "72", "death": "73", "parent": "83"}, {"id": "92", "birth": "73", "death": "73", "parent": "79"}, {"id": "93", "birth": "73", "death": "74", "parent": "79"}, {"id": "94", "birth": "73", "death": "73", "parent": "79"}, {"id": "95", "birth": "74", "death": "78", "parent": "91"}, {"id": "96", "birth": "74", "death": "74", "parent": "91"}, {"id": "97", "birth": "74", "death": "75", "parent": "91"}, {"id": "98", "birth": "75", "death": "75", "parent": "89"}, {"id": "99", "birth": "75", "death": "80", "parent": "89"}, {"id": "100", "birth": "75", "death": "76", "parent": "75"}, {"id": "101", "birth": "75", "death": "77", "parent": "75"}, {"id": "102", "birth": "75", "death": "76", "parent": "93"}, {"id": "103", "birth": "75", "death": "75", "parent": "93"}, {"id": "104", "birth": "75", "death": "75", "parent": "93"}, {"id": "105", "birth": "75", "death": "96", "parent": "16"}, {"id": "106", "birth": "75", "death": "75", "parent": "16"}, {"id": "107", "birth": "76", "death": "76", "parent": "0"}, {"id": "108", "birth": "77", "death": "78", "parent": "102"}, {"id": "109", "birth": "77", "death": "77", "parent": "102"}, {"id": "110", "birth": "77", "death": "77", "parent": "102"}, {"id": "111", "birth": "77", "death": "77", "parent": "102"}, {"id": "112", "birth": "79", "death": "80", "parent": "108"}, {"id": "113", "birth": "79", "death": "79", "parent": "108"}, {"id": "114", "birth": "79", "death": "81", "parent": "108"}, {"id": "115", "birth": "80", "death": "80", "parent": "113"}, {"id": "116", "birth": "80", "death": "80", "parent": "113"}, {"id": "117", "birth": "81", "death": "81", "parent": "99"}, {"id": "118", "birth": "81", "death": "82", "parent": "99"}, {"id": "119", "birth": "81", "death": "81", "parent": "0"}, {"id": "120", "birth": "81", "death": "82", "parent": "115"}, {"id": "121", "birth": "81", "death": "81", "parent": "115"}, {"id": "122", "birth": "82", "death": "83", "parent": "114"}, {"id": "123", "birth": "82", "death": "82", "parent": "114"}, {"id": "124", "birth": "83", "death": "83", "parent": "118"}, {"id": "125", "birth": "83", "death": "101", "parent": "118"}, {"id": "126", "birth": "83", "death": "86", "parent": "120"}, {"id": "127", "birth": "83", "death": "83", "parent": "120"}, {"id": "128", "birth": "83", "death": "83", "parent": "120"}, {"id": "129", "birth": "84", "death": "84", "parent": "128"}, {"id": "130", "birth": "84", "death": "84", "parent": "128"}, {"id": "131", "birth": "84", "death": "84", "parent": "122"}, {"id": "132", "birth": "84", "death": "85", "parent": "122"}, {"id": "133", "birth": "84", "death": "84", "parent": "128"}, {"id": "134", "birth": "85", "death": "85", "parent": "0"}, {"id": "135", "birth": "86", "death": "86", "parent": "132"}, {"id": "136", "birth": "86", "death": "86", "parent": "132"}, {"id": "137", "birth": "87", "death": "87", "parent": "0"}, {"id": "138", "birth": "87", "death": "89", "parent": "135"}, {"id": "139", "birth": "87", "death": "87", "parent": "135"}, {"id": "140", "birth": "87", "death": "88", "parent": "126"}, {"id": "141", "birth": "87", "death": "87", "parent": "126"}, {"id": "142", "birth": "87", "death": "87", "parent": "126"}, {"id": "143", "birth": "89", "death": "91", "parent": "140"}, {"id": "144", "birth": "89", "death": "90", "parent": "140"}, {"id": "145", "birth": "89", "death": "89", "parent": "0"}, {"id": "146", "birth": "90", "death": "90", "parent": "0"}, {"id": "147", "birth": "90", "death": "90", "parent": "138"}, {"id": "148", "birth": "90", "death": "90", "parent": "138"}, {"id": "149", "birth": "91", "death": "91", "parent": "147"}, {"id": "150", "birth": "91", "death": "93", "parent": "147"}, {"id": "151", "birth": "92", "death": "93", "parent": "143"}, {"id": "152", "birth": "92", "death": "92", "parent": "143"}, {"id": "153", "birth": "92", "death": "92", "parent": "0"}, {"id": "154", "birth": "94", "death": "96", "parent": "151"}, {"id": "155", "birth": "94", "death": "95", "parent": "151"}, {"id": "156", "birth": "94", "death": "95", "parent": "150"}, {"id": "157", "birth": "94", "death": "94", "parent": "150"}, {"id": "158", "birth": "95", "death": "102", "parent": "0"}, {"id": "159", "birth": "95", "death": "95", "parent": "0"}, {"id": "160", "birth": "96", "death": "98", "parent": "156"}, {"id": "161", "birth": "96", "death": "96", "parent": "156"}, {"id": "162", "birth": "96", "death": "96", "parent": "156"}, {"id": "163", "birth": "97", "death": "98", "parent": "0"}, {"id": "164", "birth": "97", "death": "101", "parent": "154"}, {"id": "165", "birth": "97", "death": "99", "parent": "154"}, {"id": "166", "birth": "97", "death": "97", "parent": "154"}, {"id": "167", "birth": "97", "death": "97", "parent": "105"}, {"id": "168", "birth": "97", "death": "97", "parent": "105"}, {"id": "169", "birth": "98", "death": "98", "parent": "166"}, {"id": "170", "birth": "98", "death": "98", "parent": "166"}, {"id": "171", "birth": "98", "death": "99", "parent": "167"}, {"id": "172", "birth": "98", "death": "100", "parent": "167"}, {"id": "173", "birth": "98", "death": "98", "parent": "166"}, {"id": "174", "birth": "99", "death": "106", "parent": "160"}, {"id": "175", "birth": "99", "death": "99", "parent": "160"}, {"id": "176", "birth": "100", "death": "103", "parent": "46"}, {"id": "177", "birth": "100", "death": "100", "parent": "46"}, {"id": "178", "birth": "101", "death": "114", "parent": "3"}, {"id": "179", "birth": "101", "death": "104", "parent": "3"}, {"id": "180", "birth": "101", "death": "114", "parent": "172"}, {"id": "181", "birth": "101", "death": "101", "parent": "172"}, {"id": "182", "birth": "102", "death": "103", "parent": "125"}, {"id": "183", "birth": "102", "death": "102", "parent": "125"}, {"id": "184", "birth": "102", "death": "102", "parent": "164"}, {"id": "185", "birth": "102", "death": "102", "parent": "164"}, {"id": "186", "birth": "102", "death": "102", "parent": "164"}, {"id": "187", "birth": "103", "death": "103", "parent": "184"}, {"id": "188", "birth": "103", "death": "104", "parent": "184"}, {"id": "189", "birth": "104", "death": "114", "parent": "182"}, {"id": "190", "birth": "104", "death": "108", "parent": "182"}, {"id": "191", "birth": "104", "death": "104", "parent": "187"}, {"id": "192", "birth": "104", "death": "104", "parent": "187"}, {"id": "193", "birth": "105", "death": "105", "parent": "179"}, {"id": "194", "birth": "105", "death": "107", "parent": "179"}, {"id": "195", "birth": "105", "death": "105", "parent": "192"}, {"id": "196", "birth": "105", "death": "106", "parent": "192"}, {"id": "197", "birth": "106", "death": "108", "parent": "193"}, {"id": "198", "birth": "106", "death": "107", "parent": "193"}, {"id": "199", "birth": "106", "death": "106", "parent": "195"}, {"id": "200", "birth": "106", "death": "106", "parent": "195"}, {"id": "201", "birth": "107", "death": "110", "parent": "199"}, {"id": "202", "birth": "107", "death": "107", "parent": "199"}, {"id": "203", "birth": "107", "death": "107", "parent": "174"}, {"id": "204", "birth": "107", "death": "111", "parent": "174"}, {"id": "205", "birth": "108", "death": "109", "parent": "194"}, {"id": "206", "birth": "108", "death": "110", "parent": "194"}, {"id": "207", "birth": "108", "death": "108", "parent": "0"}, {"id": "208", "birth": "108", "death": "108", "parent": "203"}, {"id": "209", "birth": "108", "death": "109", "parent": "203"}, {"id": "210", "birth": "109", "death": "109", "parent": "190"}, {"id": "211", "birth": "109", "death": "114", "parent": "190"}, {"id": "212", "birth": "109", "death": "109", "parent": "197"}, {"id": "213", "birth": "109", "death": "109", "parent": "197"}, {"id": "214", "birth": "109", "death": "110", "parent": "0"}, {"id": "215", "birth": "110", "death": "110", "parent": "213"}, {"id": "216", "birth": "110", "death": "110", "parent": "213"}, {"id": "217", "birth": "111", "death": "112", "parent": "215"}, {"id": "218", "birth": "111", "death": "111", "parent": "215"}, {"id": "219", "birth": "111", "death": "114", "parent": "201"}, {"id": "220", "birth": "111", "death": "111", "parent": "201"}, {"id": "221", "birth": "112", "death": "112", "parent": "204"}, {"id": "222", "birth": "112", "death": "112", "parent": "204"}, {"id": "223", "birth": "112", "death": "114", "parent": "0"}, {"id": "224", "birth": "113", "death": "114", "parent": "217"}, {"id": "225", "birth": "113", "death": "114", "parent": "217"}, {"id": "226", "birth": "113", "death": "113", "parent": "222"}, {"id": "227", "birth": "113", "death": "113", "parent": "222"}, {"id": "228", "birth": "114", "death": "114", "parent": "226"}, {"id": "229", "birth": "114", "death": "114", "parent": "226"}, {"id": "230", "birth": "114", "death": "114", "parent": "226"}]}